instawow/__init__.py
instawow/__main__.py
instawow/_github_auth.py
instawow/_import_wrapper.py
instawow/_logging.py
instawow/_version.py
instawow/config_ctx.py
instawow/definitions.py
instawow/http_ctx.py
instawow/pkg_management.py
instawow/plugins.py
instawow/progress_reporting.py
instawow/py.typed
instawow/resolvers.py
instawow/results.py
instawow/sync_ctx.py
instawow/wow_installations.py
instawow/_sources/__init__.py
instawow/_sources/cfcore.py
instawow/_sources/github.py
instawow/_sources/instawow.py
instawow/_sources/tukui.py
instawow/_sources/wago_addons.py
instawow/_sources/wowi.py
instawow/_utils/__init__.py
instawow/_utils/aio.py
instawow/_utils/attrs.py
instawow/_utils/dist_metadata.py
instawow/_utils/file.py
instawow/_utils/iteration.py
instawow/_utils/perf.py
instawow/_utils/text.py
instawow/_utils/web.py
instawow/catalogue/__init__.py
instawow/catalogue/cataloguer.py
instawow/catalogue/search.py
instawow/cli/__init__.py
instawow/cli/_helpers.py
instawow/cli/prompts.py
instawow/config/__init__.py
instawow/config/_dirs.py
instawow/config/_helpers.py
instawow/http/__init__.py
instawow/http/_cache.py
instawow/matchers/__init__.py
instawow/matchers/addon_toc.py
instawow/pkg_archives/__init__.py
instawow/pkg_archives/_download.py
instawow/pkg_db/__init__.py
instawow/pkg_db/_migrations.py
instawow/pkg_db/models.py
instawow_weakaura_updater/__init__.py
instawow_weakaura_updater/_cli.py
instawow_weakaura_updater/_custom_slpp.py
instawow_weakaura_updater/_plugin.py
instawow_weakaura_updater/_utils.py
instawow_weakaura_updater/builder.py
instawow_weakaura_updater/config.py
instawow_weakaura_updater/py.typed
instawow-7.0.0.dist-info/METADATA
instawow-7.0.0.dist-info/WHEEL
instawow-7.0.0.dist-info/entry_points.txt
instawow-7.0.0.dist-info/licenses/COPYING
instawow-7.0.0.dist-info/RECORD
