Metadata-Version: 2.4
Name: instawow
Version: 7.0.0
Summary: World of Warcraft add-on manager
Project-URL: homepage, http://github.com/layday/instawow
Author-email: layday <layday@protonmail.com>
License-Expression: GPL-3.0-or-later
License-File: COPYING
Requires-Python: >=3.12
Requires-Dist: aiohttp-client-cache>=0.12.4
Requires-Dist: aiohttp>=3.11.16
Requires-Dist: attrs>=24.2.0
Requires-Dist: cattrs>=24.1.0
Requires-Dist: click>=8.2
Requires-Dist: diskcache>=5.6.3
Requires-Dist: loguru>=0.7.3
Requires-Dist: multidict>=6.5.0
Requires-Dist: packaging>=24.1
Requires-Dist: pluggy>=1.5.0
Requires-Dist: prompt-toolkit>=3.0.47
Requires-Dist: rapidfuzz>=3.12.2
Requires-Dist: truststore>=0.10.1
Requires-Dist: typing-extensions>=4.12.2
Requires-Dist: wcwidth>=0.2.13
Requires-Dist: yarl>=1.18.3
